neoteroi/mkdocs/__init__.py
neoteroi/mkdocs/py.typed
neoteroi/mkdocs/cards/__init__.py
neoteroi/mkdocs/cards/domain.py
neoteroi/mkdocs/cards/html.py
neoteroi/mkdocs/cards/py.typed
neoteroi/mkdocs/contribs/__init__.py
neoteroi/mkdocs/contribs/domain.py
neoteroi/mkdocs/contribs/git.py
neoteroi/mkdocs/contribs/html.py
neoteroi/mkdocs/contribs/py.typed
neoteroi/mkdocs/contribs/txt.py
neoteroi/mkdocs/markdown/__init__.py
neoteroi/mkdocs/markdown/align.py
neoteroi/mkdocs/markdown/images.py
neoteroi/mkdocs/markdown/processors.py
neoteroi/mkdocs/markdown/py.typed
neoteroi/mkdocs/markdown/utils.py
neoteroi/mkdocs/markdown/data/__init__.py
neoteroi/mkdocs/markdown/data/files.py
neoteroi/mkdocs/markdown/data/source.py
neoteroi/mkdocs/markdown/data/text.py
neoteroi/mkdocs/markdown/data/web.py
neoteroi/mkdocs/markdown/tables/__init__.py
neoteroi/mkdocs/markdown/tables/spantable.py
neoteroi/mkdocs/oad/__init__.py
neoteroi/mkdocs/oad/py.typed
neoteroi/mkdocs/projects/__init__.py
neoteroi/mkdocs/projects/domain.py
neoteroi/mkdocs/projects/py.typed
neoteroi/mkdocs/projects/timeutil.py
neoteroi/mkdocs/projects/gantt/__init__.py
neoteroi/mkdocs/projects/gantt/html.py
neoteroi/mkdocs/spantable/__init__.py
neoteroi/mkdocs/spantable/py.typed
neoteroi/mkdocs/timeline/__init__.py
neoteroi/mkdocs/timeline/domain.py
neoteroi/mkdocs/timeline/html.py
neoteroi/mkdocs/timeline/py.typed
neoteroi_mkdocs-1.1.3.dist-info/METADATA
neoteroi_mkdocs-1.1.3.dist-info/WHEEL
neoteroi_mkdocs-1.1.3.dist-info/entry_points.txt
neoteroi_mkdocs-1.1.3.dist-info/licenses/LICENSE
neoteroi_mkdocs-1.1.3.dist-info/RECORD
