Metadata-Version: 2.4
Name: neoteroi-mkdocs
Version: 1.1.3
Summary: Plugins for MkDocs and Python Markdown
Project-URL: Homepage, https://github.com/Neoteroi/mkdocs-plugins
Project-URL: Bug Tracker, https://github.com/Neoteroi/mkdocs-plugins/issues
Author-email: Roberto Prevato <roberto.prevato@gmail.com>
License-File: LICENSE
Keywords: Markdown,MkDocs,OpenAPI,Swagger,documentation,extensions,plugins
Classifier: Development Status :: 5 - Production/Stable
Classifier: License :: OSI Approved :: MIT License
Classifier: Operating System :: OS Independent
Classifier: Programming Language :: Python :: 3
Classifier: Programming Language :: Python :: 3.7
Classifier: Programming Language :: Python :: 3.8
Classifier: Programming Language :: Python :: 3.9
Classifier: Programming Language :: Python :: 3.10
Classifier: Programming Language :: Python :: 3.11
Classifier: Programming Language :: Python :: 3.12
Classifier: Programming Language :: Python :: 3.13
Requires-Python: >=3.7
Requires-Dist: click
Requires-Dist: essentials-openapi>=1.2.1
Requires-Dist: httpx
Requires-Dist: jinja2
Requires-Dist: mkdocs
Requires-Dist: rich
